numtext/__init__.py
numtext/cli.py
numtext/numtext.py
numtext-0.2.1.dist-info/AUTHORS.rst
numtext-0.2.1.dist-info/METADATA
numtext-0.2.1.dist-info/WHEEL
numtext-0.2.1.dist-info/entry_points.txt
numtext-0.2.1.dist-info/top_level.txt
numtext-0.2.1.dist-info/RECORD
