Metadata-Version: 2.1
Name: numtext
Version: 0.2.1
Summary: Python Package to convert number to text
Home-page: https://github.com/insumanth/numtext
Author: Sumanth
Author-email: sumanthreddystar@gmail.com
License: UNKNOWN
Keywords: numtext
Platform: UNKNOWN
Classifier: Development Status :: 2 - Pre-Alpha
Classifier: Intended Audience :: Developers
Classifier: Natural Language :: English
Classifier: Programming Language :: Python :: 3
Classifier: Programming Language :: Python :: 3.6
Classifier: Programming Language :: Python :: 3.7
Classifier: Programming Language :: Python :: 3.8
Requires-Python: >=3.6
